fastdot/__init__.py
fastdot/_nbdev.py
fastdot/core.py
fastdot-0.1.4.dist-info/LICENSE
fastdot-0.1.4.dist-info/METADATA
fastdot-0.1.4.dist-info/WHEEL
fastdot-0.1.4.dist-info/entry_points.txt
fastdot-0.1.4.dist-info/top_level.txt
fastdot-0.1.4.dist-info/RECORD
