Metadata-Version: 2.1
Name: fastdot
Version: 0.1.4
Summary: A simple wrapper over `pydot` which fixes some sharp edges
Home-page: https://github.com/fastai/fastdot/tree/master/
Author: Jeremy Howard
Author-email: info@fast.ai
License: Apache Software License 2.0
Keywords: fast.ai graph graphviz
Platform: UNKNOWN
Classifier: Development Status :: 4 - Beta
Classifier: Intended Audience :: Developers
Classifier: License :: OSI Approved :: Apache Software License
Classifier: Natural Language :: English
Classifier: Programming Language :: Python :: 3.6
Classifier: Programming Language :: Python :: 3.7
Classifier: Programming Language :: Python :: 3.8
Requires-Python: >=3.6
Requires-Dist: pip
Requires-Dist: packaging
Requires-Dist: pydot
Requires-Dist: fastcore
Requires-Dist: matplotlib
Requires-Dist: dataclasses
Provides-Extra: dev
